vedic_crypto/__init__.py
vedic_crypto/crypto.py
VedicCrypto-0.1.1.dist-info/LICENSE.md
VedicCrypto-0.1.1.dist-info/METADATA
VedicCrypto-0.1.1.dist-info/WHEEL
VedicCrypto-0.1.1.dist-info/top_level.txt
VedicCrypto-0.1.1.dist-info/RECORD
